adafruit_amg88xx.py
adafruit_circuitpython_amg88xx-1.2.26.dist-info/licenses/LICENSE
adafruit_circuitpython_amg88xx-1.2.26.dist-info/METADATA
adafruit_circuitpython_amg88xx-1.2.26.dist-info/WHEEL
adafruit_circuitpython_amg88xx-1.2.26.dist-info/top_level.txt
adafruit_circuitpython_amg88xx-1.2.26.dist-info/RECORD
